{
    "/js/app.js": "/js/app.js",
    "/css/normalize.css": "/css/normalize.css",
    "/css/app.css": "/css/app.css",
    "/js/app.2acab9eb779b2817a7db.hot-update.js": "/js/app.2acab9eb779b2817a7db.hot-update.js",
    "/js/app.bae1e40244fd6282eb1d.hot-update.js": "/js/app.bae1e40244fd6282eb1d.hot-update.js",
    "/js/app.88b2b8a5b16348b213ba.hot-update.js": "/js/app.88b2b8a5b16348b213ba.hot-update.js",
    "/js/app.37db1a3365cb5fa1258b.hot-update.js": "/js/app.37db1a3365cb5fa1258b.hot-update.js",
    "/js/app.d794cd5386e111d76a7d.hot-update.js": "/js/app.d794cd5386e111d76a7d.hot-update.js",
    "/js/app.9c690d5f451d55cc45a6.hot-update.js": "/js/app.9c690d5f451d55cc45a6.hot-update.js",
    "/js/app.476c13c60544cd019177.hot-update.js": "/js/app.476c13c60544cd019177.hot-update.js",
    "/js/app.c22ca53aa521a0a1cbd3.hot-update.js": "/js/app.c22ca53aa521a0a1cbd3.hot-update.js",
    "/js/app.4f2d5e60989349c2847a.hot-update.js": "/js/app.4f2d5e60989349c2847a.hot-update.js",
    "/js/app.bee0830147b38072ed46.hot-update.js": "/js/app.bee0830147b38072ed46.hot-update.js",
    "/js/app.7b08509b6b142e502164.hot-update.js": "/js/app.7b08509b6b142e502164.hot-update.js",
    "/js/app.4eb9d6a59ddd7c0e6441.hot-update.js": "/js/app.4eb9d6a59ddd7c0e6441.hot-update.js",
    "/js/app.a045d5bfa655ba939a6a.hot-update.js": "/js/app.a045d5bfa655ba939a6a.hot-update.js",
    "/js/app.b1ddbd8fc0ac65456bb5.hot-update.js": "/js/app.b1ddbd8fc0ac65456bb5.hot-update.js",
    "/js/app.6affa26725173da11380.hot-update.js": "/js/app.6affa26725173da11380.hot-update.js",
    "/js/app.469835e89c691c66ef34.hot-update.js": "/js/app.469835e89c691c66ef34.hot-update.js",
    "/js/app.4c8b8a87221a3ec841f1.hot-update.js": "/js/app.4c8b8a87221a3ec841f1.hot-update.js",
    "/js/app.c67d12c89e764410a107.hot-update.js": "/js/app.c67d12c89e764410a107.hot-update.js",
    "/js/app.a248e70ae3abe4a93019.hot-update.js": "/js/app.a248e70ae3abe4a93019.hot-update.js",
    "/js/app.271d505a046ba46af2e1.hot-update.js": "/js/app.271d505a046ba46af2e1.hot-update.js",
    "/js/app.2786209ba2b5bc12d1ea.hot-update.js": "/js/app.2786209ba2b5bc12d1ea.hot-update.js",
    "/js/app.dbdd7d7502b0c9edd1ae.hot-update.js": "/js/app.dbdd7d7502b0c9edd1ae.hot-update.js",
    "/js/app.ca1d053baa0eb7bdcda7.hot-update.js": "/js/app.ca1d053baa0eb7bdcda7.hot-update.js",
    "/js/app.93f6db33bc57c001e9d8.hot-update.js": "/js/app.93f6db33bc57c001e9d8.hot-update.js",
    "/js/app.f6512137f2e10adfdd3a.hot-update.js": "/js/app.f6512137f2e10adfdd3a.hot-update.js",
    "/js/app.ef2e0d8bde1788e26d32.hot-update.js": "/js/app.ef2e0d8bde1788e26d32.hot-update.js",
    "/js/app.3b999f6622e744b508e7.hot-update.js": "/js/app.3b999f6622e744b508e7.hot-update.js",
    "/js/app.454f9b648c84ebd9afde.hot-update.js": "/js/app.454f9b648c84ebd9afde.hot-update.js",
    "/js/app.9587d3c09fa2c7728830.hot-update.js": "/js/app.9587d3c09fa2c7728830.hot-update.js",
    "/js/app.156305c9cb0da690741c.hot-update.js": "/js/app.156305c9cb0da690741c.hot-update.js",
    "/js/app.40263f0a64ba2d0faf7f.hot-update.js": "/js/app.40263f0a64ba2d0faf7f.hot-update.js",
    "/js/app.d1539e46b1195b39e180.hot-update.js": "/js/app.d1539e46b1195b39e180.hot-update.js",
    "/js/app.900a2fb787f4d187e5cc.hot-update.js": "/js/app.900a2fb787f4d187e5cc.hot-update.js",
    "/js/app.f79bc055c3895b06f35f.hot-update.js": "/js/app.f79bc055c3895b06f35f.hot-update.js",
    "/js/app.5cab211070e0bbbc0344.hot-update.js": "/js/app.5cab211070e0bbbc0344.hot-update.js",
    "/js/app.c2f0e3e783ea56875059.hot-update.js": "/js/app.c2f0e3e783ea56875059.hot-update.js",
    "/js/app.58d0251a22117ad813b8.hot-update.js": "/js/app.58d0251a22117ad813b8.hot-update.js",
    "/js/app.16b1e0070f8a581239b6.hot-update.js": "/js/app.16b1e0070f8a581239b6.hot-update.js",
    "/js/app.dcaa6d2759ce29ac7773.hot-update.js": "/js/app.dcaa6d2759ce29ac7773.hot-update.js",
    "/js/app.6ed423feb199bd82c9af.hot-update.js": "/js/app.6ed423feb199bd82c9af.hot-update.js",
    "/js/app.503765be08d7a5e4dc2d.hot-update.js": "/js/app.503765be08d7a5e4dc2d.hot-update.js",
    "/js/app.9c103d325d88ef2236cd.hot-update.js": "/js/app.9c103d325d88ef2236cd.hot-update.js",
    "/js/app.2373e536e12c394d6e86.hot-update.js": "/js/app.2373e536e12c394d6e86.hot-update.js",
    "/js/app.d77419fc326e536cfb57.hot-update.js": "/js/app.d77419fc326e536cfb57.hot-update.js",
    "/js/app.1d0198e3fb454469028f.hot-update.js": "/js/app.1d0198e3fb454469028f.hot-update.js",
    "/js/app.a4e4cfb9e4ca6aa027c7.hot-update.js": "/js/app.a4e4cfb9e4ca6aa027c7.hot-update.js",
    "/js/app.4d304bf078f0bb9a3f5c.hot-update.js": "/js/app.4d304bf078f0bb9a3f5c.hot-update.js",
    "/js/app.81726048207be39e9bb7.hot-update.js": "/js/app.81726048207be39e9bb7.hot-update.js",
    "/js/app.a70ef6bbc2c850c8f3c0.hot-update.js": "/js/app.a70ef6bbc2c850c8f3c0.hot-update.js",
    "/js/app.38577dc8e597645cc008.hot-update.js": "/js/app.38577dc8e597645cc008.hot-update.js",
    "/js/app.8f35eb7ab550568b5e4e.hot-update.js": "/js/app.8f35eb7ab550568b5e4e.hot-update.js",
    "/js/app.3bca7e0c6acbd40cda52.hot-update.js": "/js/app.3bca7e0c6acbd40cda52.hot-update.js",
    "/js/app.aeecd72f23133c7b3786.hot-update.js": "/js/app.aeecd72f23133c7b3786.hot-update.js",
    "/js/app.8968102efca772d63779.hot-update.js": "/js/app.8968102efca772d63779.hot-update.js",
    "/js/app.3a846a4a9b8df7bb9e92.hot-update.js": "/js/app.3a846a4a9b8df7bb9e92.hot-update.js",
    "/js/app.b4ce887072d0d90fcb30.hot-update.js": "/js/app.b4ce887072d0d90fcb30.hot-update.js",
    "/js/app.951fb5b8f9dc8f2c0f31.hot-update.js": "/js/app.951fb5b8f9dc8f2c0f31.hot-update.js",
    "/js/app.63d6974c542a139ad2d6.hot-update.js": "/js/app.63d6974c542a139ad2d6.hot-update.js",
    "/js/app.6c2ba569d9cc94957c5f.hot-update.js": "/js/app.6c2ba569d9cc94957c5f.hot-update.js",
    "/js/app.be85388ac870ee02608b.hot-update.js": "/js/app.be85388ac870ee02608b.hot-update.js",
    "/js/app.3ad5261626a46477d71a.hot-update.js": "/js/app.3ad5261626a46477d71a.hot-update.js",
    "/js/app.4c13889f0973624f7b96.hot-update.js": "/js/app.4c13889f0973624f7b96.hot-update.js",
    "/js/app.3605072ac81e7424878c.hot-update.js": "/js/app.3605072ac81e7424878c.hot-update.js",
    "/js/app.11b92257219bcea8feb1.hot-update.js": "/js/app.11b92257219bcea8feb1.hot-update.js",
    "/js/app.6dbede72099c450e9e11.hot-update.js": "/js/app.6dbede72099c450e9e11.hot-update.js",
    "/js/app.3ff652901abdaaf01aa8.hot-update.js": "/js/app.3ff652901abdaaf01aa8.hot-update.js",
    "/js/app.a81ece647e96cee5acba.hot-update.js": "/js/app.a81ece647e96cee5acba.hot-update.js",
    "/js/app.ae2c88adba6058254a8c.hot-update.js": "/js/app.ae2c88adba6058254a8c.hot-update.js",
    "/js/app.9f2f8d9f2c309f61e476.hot-update.js": "/js/app.9f2f8d9f2c309f61e476.hot-update.js",
    "/js/app.bf40a0d3263c17404599.hot-update.js": "/js/app.bf40a0d3263c17404599.hot-update.js",
    "/js/app.ae06d141c67cfa44de01.hot-update.js": "/js/app.ae06d141c67cfa44de01.hot-update.js",
    "/js/app.e1875736e9a05d36dba0.hot-update.js": "/js/app.e1875736e9a05d36dba0.hot-update.js",
    "/js/app.7619d54f8808ac01f312.hot-update.js": "/js/app.7619d54f8808ac01f312.hot-update.js",
    "/js/app.b8a77689b1dee625ac19.hot-update.js": "/js/app.b8a77689b1dee625ac19.hot-update.js",
    "/js/app.5b5b9c3ecf181b94da25.hot-update.js": "/js/app.5b5b9c3ecf181b94da25.hot-update.js",
    "/js/app.9b6f77567cc20e267502.hot-update.js": "/js/app.9b6f77567cc20e267502.hot-update.js",
    "/js/app.f743e31770dbd72b4b6f.hot-update.js": "/js/app.f743e31770dbd72b4b6f.hot-update.js",
    "/js/app.885cc76a068ab45aa588.hot-update.js": "/js/app.885cc76a068ab45aa588.hot-update.js",
    "/js/app.87ad0541b8796c10c578.hot-update.js": "/js/app.87ad0541b8796c10c578.hot-update.js",
    "/js/app.bc678d6a8f721627af1d.hot-update.js": "/js/app.bc678d6a8f721627af1d.hot-update.js",
    "/js/app.c39580570307fc00de01.hot-update.js": "/js/app.c39580570307fc00de01.hot-update.js",
    "/js/app.2fc378ffb6ef4022cd57.hot-update.js": "/js/app.2fc378ffb6ef4022cd57.hot-update.js",
    "/js/app.a9ed6d0ff9fc67e78c60.hot-update.js": "/js/app.a9ed6d0ff9fc67e78c60.hot-update.js",
    "/js/app.d92729181ccff6493cbe.hot-update.js": "/js/app.d92729181ccff6493cbe.hot-update.js",
    "/js/app.115fd15296d9d90972a1.hot-update.js": "/js/app.115fd15296d9d90972a1.hot-update.js",
    "/js/app.89f8c492faa0d1f9de82.hot-update.js": "/js/app.89f8c492faa0d1f9de82.hot-update.js",
    "/js/app.efbf4430e2d3b5ff6a88.hot-update.js": "/js/app.efbf4430e2d3b5ff6a88.hot-update.js",
    "/js/app.65bc8bca664c1a9825f4.hot-update.js": "/js/app.65bc8bca664c1a9825f4.hot-update.js",
    "/js/app.bb6da38bda319e9a1305.hot-update.js": "/js/app.bb6da38bda319e9a1305.hot-update.js",
    "/js/app.6718bb292b5e8ab00f95.hot-update.js": "/js/app.6718bb292b5e8ab00f95.hot-update.js",
    "/js/app.02e00d7975e0a79a3871.hot-update.js": "/js/app.02e00d7975e0a79a3871.hot-update.js",
    "/js/app.95c05a5e976bcbc9eedc.hot-update.js": "/js/app.95c05a5e976bcbc9eedc.hot-update.js",
    "/js/app.7ad25de22e163b6b1bef.hot-update.js": "/js/app.7ad25de22e163b6b1bef.hot-update.js",
    "/js/app.240db5fddc4a7d27bcdb.hot-update.js": "/js/app.240db5fddc4a7d27bcdb.hot-update.js",
    "/js/app.eedc352cf2c55ada48b0.hot-update.js": "/js/app.eedc352cf2c55ada48b0.hot-update.js",
    "/js/app.e42c425a5ae40f8cbe03.hot-update.js": "/js/app.e42c425a5ae40f8cbe03.hot-update.js",
    "/js/app.a0db43806d20eccf969f.hot-update.js": "/js/app.a0db43806d20eccf969f.hot-update.js",
    "/js/app.346bf7a7ad4500718bc1.hot-update.js": "/js/app.346bf7a7ad4500718bc1.hot-update.js",
    "/js/app.1ee7b90d8db7f68692e9.hot-update.js": "/js/app.1ee7b90d8db7f68692e9.hot-update.js",
    "/js/app.7b8520065198ee00b3ba.hot-update.js": "/js/app.7b8520065198ee00b3ba.hot-update.js",
    "/js/app.0d975a468ac21a3735f4.hot-update.js": "/js/app.0d975a468ac21a3735f4.hot-update.js",
    "/js/app.5b656e432d2503f87323.hot-update.js": "/js/app.5b656e432d2503f87323.hot-update.js",
    "/js/app.3bf77788835434cb67a2.hot-update.js": "/js/app.3bf77788835434cb67a2.hot-update.js",
    "/js/app.e4238757e538a98e2e7d.hot-update.js": "/js/app.e4238757e538a98e2e7d.hot-update.js",
    "/js/app.f77333627930ae605f71.hot-update.js": "/js/app.f77333627930ae605f71.hot-update.js",
    "/js/app.9f3d805b4033df77a19b.hot-update.js": "/js/app.9f3d805b4033df77a19b.hot-update.js",
    "/js/app.a4ecfb9edd712df0b6f6.hot-update.js": "/js/app.a4ecfb9edd712df0b6f6.hot-update.js",
    "/js/app.b9ba93a1d3bed49fb28b.hot-update.js": "/js/app.b9ba93a1d3bed49fb28b.hot-update.js",
    "/js/app.8a89b7bdbb73c177dbe7.hot-update.js": "/js/app.8a89b7bdbb73c177dbe7.hot-update.js",
    "/js/app.4ead5122400918ca3cba.hot-update.js": "/js/app.4ead5122400918ca3cba.hot-update.js",
    "/js/app.0e11936d680609cbef4e.hot-update.js": "/js/app.0e11936d680609cbef4e.hot-update.js",
    "/js/app.21fdf76750899d16e375.hot-update.js": "/js/app.21fdf76750899d16e375.hot-update.js",
    "/js/app.3c116d034237ae778c69.hot-update.js": "/js/app.3c116d034237ae778c69.hot-update.js",
    "/js/app.9ef4cd899e6dcba106b4.hot-update.js": "/js/app.9ef4cd899e6dcba106b4.hot-update.js",
    "/js/app.d8f28a5aa9ea4f3044ab.hot-update.js": "/js/app.d8f28a5aa9ea4f3044ab.hot-update.js",
    "/js/app.e2f1c9ed717b59280f63.hot-update.js": "/js/app.e2f1c9ed717b59280f63.hot-update.js",
    "/js/app.2f0f621e65058abf6942.hot-update.js": "/js/app.2f0f621e65058abf6942.hot-update.js",
    "/js/app.4b7336cd8a8dfadd3d64.hot-update.js": "/js/app.4b7336cd8a8dfadd3d64.hot-update.js",
    "/js/app.128c12205e9d2ef3fe27.hot-update.js": "/js/app.128c12205e9d2ef3fe27.hot-update.js",
    "/js/app.71784f234ac5e4030521.hot-update.js": "/js/app.71784f234ac5e4030521.hot-update.js",
    "/js/app.05f625f6dec81aa8164f.hot-update.js": "/js/app.05f625f6dec81aa8164f.hot-update.js",
    "/js/app.6cbcc3648fbcccc02285.hot-update.js": "/js/app.6cbcc3648fbcccc02285.hot-update.js",
    "/js/app.7a0238f905eb55cf3a76.hot-update.js": "/js/app.7a0238f905eb55cf3a76.hot-update.js",
    "/js/app.c4762879871783ba5819.hot-update.js": "/js/app.c4762879871783ba5819.hot-update.js",
    "/js/app.22c5c1fabf9c5104eab5.hot-update.js": "/js/app.22c5c1fabf9c5104eab5.hot-update.js",
    "/js/app.5ad953066c220ecc0d84.hot-update.js": "/js/app.5ad953066c220ecc0d84.hot-update.js",
    "/js/app.3f0edf65290b635faf0e.hot-update.js": "/js/app.3f0edf65290b635faf0e.hot-update.js",
    "/js/app.58bf6813ebc82265a0d3.hot-update.js": "/js/app.58bf6813ebc82265a0d3.hot-update.js",
    "/js/app.4b6a59e284f0c0856e18.hot-update.js": "/js/app.4b6a59e284f0c0856e18.hot-update.js",
    "/js/app.6c6580fdc3b630b8b983.hot-update.js": "/js/app.6c6580fdc3b630b8b983.hot-update.js",
    "/js/app.9f56b5328ccb6cc36691.hot-update.js": "/js/app.9f56b5328ccb6cc36691.hot-update.js",
    "/js/app.d3dcdbc739d34bc4d1e9.hot-update.js": "/js/app.d3dcdbc739d34bc4d1e9.hot-update.js",
    "/js/app.35de7fbf8c4b637fa93d.hot-update.js": "/js/app.35de7fbf8c4b637fa93d.hot-update.js",
    "/js/app.579ad8fffb486f5e7234.hot-update.js": "/js/app.579ad8fffb486f5e7234.hot-update.js",
    "/js/app.0fd37247cd412a1ce481.hot-update.js": "/js/app.0fd37247cd412a1ce481.hot-update.js",
    "/js/app.764f039f9cc162a9a1e6.hot-update.js": "/js/app.764f039f9cc162a9a1e6.hot-update.js",
    "/js/app.34d0b7e8751d70428b75.hot-update.js": "/js/app.34d0b7e8751d70428b75.hot-update.js",
    "/js/app.bbbbf93ac601d041f945.hot-update.js": "/js/app.bbbbf93ac601d041f945.hot-update.js",
    "/js/app.615114cb0989c7d974c7.hot-update.js": "/js/app.615114cb0989c7d974c7.hot-update.js",
    "/js/app.35ac1ca179189693cb26.hot-update.js": "/js/app.35ac1ca179189693cb26.hot-update.js",
    "/js/app.5f46009bdc5bd21e582e.hot-update.js": "/js/app.5f46009bdc5bd21e582e.hot-update.js",
    "/js/app.6f623bf4697c77d6ff87.hot-update.js": "/js/app.6f623bf4697c77d6ff87.hot-update.js",
    "/js/app.f96604e09d76dbda4ade.hot-update.js": "/js/app.f96604e09d76dbda4ade.hot-update.js",
    "/js/app.e19115e8886fcc78b9aa.hot-update.js": "/js/app.e19115e8886fcc78b9aa.hot-update.js",
    "/js/app.06d709a6acef89655480.hot-update.js": "/js/app.06d709a6acef89655480.hot-update.js",
    "/js/app.aca606098beca2a1ad00.hot-update.js": "/js/app.aca606098beca2a1ad00.hot-update.js",
    "/js/app.08c1853aeab0451e73c2.hot-update.js": "/js/app.08c1853aeab0451e73c2.hot-update.js",
    "/js/app.0a079c8138e7e5aeff48.hot-update.js": "/js/app.0a079c8138e7e5aeff48.hot-update.js",
    "/js/app.678ff2bf3a4f302ec346.hot-update.js": "/js/app.678ff2bf3a4f302ec346.hot-update.js",
    "/js/app.a563bfd389fe8e573a2b.hot-update.js": "/js/app.a563bfd389fe8e573a2b.hot-update.js",
    "/js/app.52b702da1016c05b9a44.hot-update.js": "/js/app.52b702da1016c05b9a44.hot-update.js",
    "/js/app.88fe4038a2704d737506.hot-update.js": "/js/app.88fe4038a2704d737506.hot-update.js",
    "/js/app.276948c1e080a94c71ca.hot-update.js": "/js/app.276948c1e080a94c71ca.hot-update.js",
    "/js/app.1b7fecdcff76c1abe7f2.hot-update.js": "/js/app.1b7fecdcff76c1abe7f2.hot-update.js",
    "/js/app.7db27449033c08f68c83.hot-update.js": "/js/app.7db27449033c08f68c83.hot-update.js",
    "/js/app.3de93914cd562d895394.hot-update.js": "/js/app.3de93914cd562d895394.hot-update.js",
    "/js/app.04d5eba98170501118ed.hot-update.js": "/js/app.04d5eba98170501118ed.hot-update.js",
    "/js/app.f63708b701142325388e.hot-update.js": "/js/app.f63708b701142325388e.hot-update.js",
    "/js/app.b7bcff23bd212d3a6f78.hot-update.js": "/js/app.b7bcff23bd212d3a6f78.hot-update.js",
    "/js/app.415216354c3fa4a84601.hot-update.js": "/js/app.415216354c3fa4a84601.hot-update.js",
    "/js/app.310fd3e903b34b3091b6.hot-update.js": "/js/app.310fd3e903b34b3091b6.hot-update.js",
    "/js/app.4eac4618841b394cef9d.hot-update.js": "/js/app.4eac4618841b394cef9d.hot-update.js",
    "/js/app.d78535f46293f902be53.hot-update.js": "/js/app.d78535f46293f902be53.hot-update.js",
    "/js/app.d18a299d9898af6e120f.hot-update.js": "/js/app.d18a299d9898af6e120f.hot-update.js",
    "/js/app.4c3dba217cfcf35229ae.hot-update.js": "/js/app.4c3dba217cfcf35229ae.hot-update.js",
    "/js/app.3cc48910c2a7f5e5991c.hot-update.js": "/js/app.3cc48910c2a7f5e5991c.hot-update.js",
    "/js/app.6bfea5610f4f292e0f2f.hot-update.js": "/js/app.6bfea5610f4f292e0f2f.hot-update.js",
    "/js/app.9d44ee273e17fa09a9cb.hot-update.js": "/js/app.9d44ee273e17fa09a9cb.hot-update.js",
    "/js/app.3942240082bcce5a1f76.hot-update.js": "/js/app.3942240082bcce5a1f76.hot-update.js",
    "/js/app.9c4f223f2d148a7b4217.hot-update.js": "/js/app.9c4f223f2d148a7b4217.hot-update.js",
    "/js/app.71e74e6e8f866f1ae532.hot-update.js": "/js/app.71e74e6e8f866f1ae532.hot-update.js",
    "/js/app.c364d373ca04e00ae263.hot-update.js": "/js/app.c364d373ca04e00ae263.hot-update.js",
    "/js/app.2b00ac9c869a9ea56d4c.hot-update.js": "/js/app.2b00ac9c869a9ea56d4c.hot-update.js"
}
